{
  "version": 2,
  "type": "rule",
  "id": "alcohol_dependence_rule",
  "title": "음주 문제 (알코올 의존 의심)",
  "category": "음주 문제",
  "targetDiagnosis": "알코올 사용장애(중증) 의심 (Suspected severe alcohol use disorder)",
  "variant": "금단 증상·해장술 동반 의존형",
  "description": "아침에 손이 떨려 해장술을 마시고, 줄이려 해도 번번이 실패하는 규칙입니다.",
  "tags": [
    "음주",
    "알코올의존",
    "금단",
    "CAGE"
  ],
  "sourceTextFile": "(자체 제작 — Guide to Real CPX 5판 CPX 04 감별 지식 참조, 서사·인물 창작)",
  "demographicsRule": {
    "fixed": {
      "location": "외래"
    },
    "recommended": {
      "gender": "남성 우세",
      "age": "45~60세"
    },
    "randomizable": [
      "성별",
      "이름",
      "경제적 수준",
      "학력 수준",
      "직업",
      "키",
      "몸무게"
    ],
    "mustAbsent": []
  },
  "scenarioRule": {
    "caseSummary": "20년 넘게 거의 매일 소주 1~2병을 마셔온 환자. 최근 아침마다 손이 떨리고 식은땀이 나 해장술로 달래며, 여러 번 줄이려 했지만 번번이 실패했다. 아내의 성화에 못 이겨 내원했다.",
    "mustInclude": [
      "매일 소주 1~2병, 20년+",
      "아침 손떨림·식은땀 → 해장술(금단)",
      "절주 시도 반복 실패",
      "내성(양이 늘어옴)",
      "음주로 부부 갈등·지각 반복",
      "필름 끊김 잦음"
    ],
    "preferredVariants": [
      "'술은 내 유일한 낙'이라며 방어적",
      "속쓰림·간수치 지적받은 적 있음"
    ],
    "mustAbsent": [
      "환각·경련(아직 없음)",
      "자살 사고(물으면 없음)",
      "다른 약물 사용"
    ]
  },
  "pastHistoryRule": {
    "mustInclude": [
      "작년 검진 간수치 상승 지적(추적 안 함)"
    ],
    "mustAbsent": [
      "간경변 진단",
      "경련성 질환",
      "다른 약물 사용"
    ]
  },
  "familyHistoryRule": {
    "recommended": [
      "아버지도 술 문제"
    ],
    "mustAbsent": []
  },
  "socialHistoryRule": {
    "fixed": [
      "매일 소주 1~2병",
      "흡연 있음"
    ],
    "recommended": [
      "자영업(술자리 잦음)"
    ]
  },
  "physicalExamRule": [
    {
      "item": "활력징후",
      "method": "활력징후 확인",
      "expectedFinding": "혈압 다소 높음, 맥박 96회",
      "polarity": "positive"
    },
    {
      "item": "금단 징후",
      "method": "손떨림·발한 관찰",
      "expectedFinding": "양손 미세 떨림 (+)",
      "polarity": "positive"
    },
    {
      "item": "복부·간",
      "method": "복부 진찰(간 촉진)",
      "expectedFinding": "간이 2횡지 촉지되며 가장자리 둔함",
      "polarity": "positive"
    },
    {
      "item": "황달·영양",
      "method": "공막 황달·영양 상태 확인",
      "expectedFinding": "황달 없음, 안면 홍조·모세혈관 확장",
      "polarity": "positive"
    }
  ],
  "liveApiContext": {
    "patientContextFocus": "알코올 의존이 의심되는 환자. '해장술', '절주 실패', '아침 떨림'은 해당 주제를 질문받았을 때 공개한다. 방어적이지만 비판단적으로 접근하면 솔직해진다.",
    "answerPolicy": [
      "먼저 병명을 말하지 않는다.",
      "학생이 묻는 항목에 대해서만 환자 관점에서 짧게 답한다.",
      "고정-부재 단서는 질문받으면 없다고 답한다.",
      "처음엔 음주량을 축소해 말하다가('소주 반 병쯤'), 구체적으로 재차 물으면 사실대로 말한다."
    ],
    "positiveClues": [
      "매일 소주 1~2병·20년",
      "해장술·아침 떨림(금단)",
      "절주 실패·내성",
      "블랙아웃",
      "간수치 지적·간비대",
      "가족력"
    ],
    "negativeClues": [
      "환각·경련 없음",
      "다른 약물 없음",
      "자살 사고 없음"
    ]
  },
  "evaluationUse": {
    "mustAsk": [
      "음주량·빈도(구체적)",
      "금단 증상(아침 떨림·해장술)",
      "조절 실패·내성",
      "음주로 인한 문제",
      "블랙아웃",
      "간 관련 증상·검진",
      "가족력·기분·자살 스크리닝"
    ],
    "positiveClues": [
      "매일 소주 1~2병·20년",
      "해장술·아침 떨림(금단)",
      "절주 실패·내성",
      "블랙아웃",
      "간수치 지적·간비대"
    ],
    "negativeClues": [
      "환각·경련 없음",
      "다른 약물 없음",
      "자살 사고 없음"
    ],
    "educationTopics": [
      "알코올 의존 설명 — 의지가 아닌 치료가 필요한 뇌 질환",
      "갑작스러운 혼자 단주의 금단 위험(경련·섬망) — 의학적 관리 하 단주",
      "간기능 등 검사와 치료 프로그램(약물·상담·자조모임) 안내",
      "가족 참여와 추적 약속"
    ]
  },
  "additionalPromptRule": [],
  "ruleText": "# 증례명 : 음주 문제 (알코올 의존 의심) — 알코올 사용장애(중증) 의심 (Suspected severe alcohol use disorder)\n\n- 인적사항 - 성별: 랜덤(남성 우세), 나이: 45~60세 권장, 장소: 외래, 나머지 랜덤\n\n- 사례 요약 - 20년 넘게 거의 매일 소주 1~2병을 마셔온 환자. 최근 아침마다 손이 떨리고 식은땀이 나 해장술로 달래며, 여러 번 줄이려 했지만 번번이 실패했다. 아내의 성화에 못 이겨 내원했다.\n\n- 감정 상태 - 아내 성화로 마지못해 옴. 방어적이지만 아침 떨림은 스스로도 겁남.\n\n- 현 병력 - 소주 1~2병/일, 20년+. 아침 손떨림·식은땀 → 해장술. 절주 실패 반복. 내성. 부부 갈등·지각. 블랙아웃 잦음. 속쓰림, 작년 검진 간수치 높다는 말. 환각·경련 없음. 자살 사고 없음.\n\n- 과거력 - 작년 검진 간수치 상승 지적(추적 안 함). 그 외 진단력 없음.\n\n- 가족력 - 아버지도 술 문제\n\n- 사회력 - 자영업, 흡연 있음, 매일 음주(고정)\n\n- 신체진찰 - 활력징후 확인: 혈압 다소 높음, 맥박 96회 / 손떨림·발한 관찰: 양손 미세 떨림 (+) / 복부 진찰(간 촉진): 간이 2횡지 촉지되며 가장자리 둔함 / 공막 황달·영양 상태 확인: 황달 없음, 안면 홍조·모세혈관 확장\n\n추가 질문 \"술을 딱 끊으면 되는 것 아닙니까? 무슨 치료까지 해요?\"",
  "rawRuleText": "# 증례명 : 음주 문제 (알코올 의존 의심) — 알코올 사용장애(중증) 의심 (Suspected severe alcohol use disorder)\n\n- 인적사항 - 성별: 랜덤(남성 우세), 나이: 45~60세 권장, 장소: 외래, 나머지 랜덤\n\n- 사례 요약 - 20년 넘게 거의 매일 소주 1~2병을 마셔온 환자. 최근 아침마다 손이 떨리고 식은땀이 나 해장술로 달래며, 여러 번 줄이려 했지만 번번이 실패했다. 아내의 성화에 못 이겨 내원했다.\n\n- 감정 상태 - 아내 성화로 마지못해 옴. 방어적이지만 아침 떨림은 스스로도 겁남.\n\n- 현 병력 - 소주 1~2병/일, 20년+. 아침 손떨림·식은땀 → 해장술. 절주 실패 반복. 내성. 부부 갈등·지각. 블랙아웃 잦음. 속쓰림, 작년 검진 간수치 높다는 말. 환각·경련 없음. 자살 사고 없음.\n\n- 과거력 - 작년 검진 간수치 상승 지적(추적 안 함). 그 외 진단력 없음.\n\n- 가족력 - 아버지도 술 문제\n\n- 사회력 - 자영업, 흡연 있음, 매일 음주(고정)\n\n- 신체진찰 - 활력징후 확인: 혈압 다소 높음, 맥박 96회 / 손떨림·발한 관찰: 양손 미세 떨림 (+) / 복부 진찰(간 촉진): 간이 2횡지 촉지되며 가장자리 둔함 / 공막 황달·영양 상태 확인: 황달 없음, 안면 홍조·모세혈관 확장\n\n추가 질문 \"술을 딱 끊으면 되는 것 아닙니까? 무슨 치료까지 해요?\""
}
