{
  "version": 2,
  "type": "rule",
  "id": "meniere_rule",
  "title": "어지럼 (메니에르병 의심)",
  "category": "어지럼",
  "classificationStandard": "주호소 분류 근거: 한국보건의료인국가시험원(국시원) 공개 CPX 진료문항 항목표 CPX 52 '어지럼' — 국가시험 공개 표준 분류이며 특정 교재의 편집·배열을 따른 것이 아님. 개별 시나리오의 인물·서사·대사·수치는 자체 창작.",
  "targetDiagnosis": "메니에르병 의심 (Suspected Meniere disease)",
  "variant": "반복 회전성 어지럼 + 이명·난청·귀 충만감형",
  "description": "한쪽 귀가 먹먹하고 윙윙거리다 세상이 도는 발작이 반복되는 규칙입니다.",
  "tags": [
    "어지럼",
    "메니에르",
    "이명",
    "난청"
  ],
  "sourceTextFile": "(자체 제작 — Guide to Real CPX 5판 CPX 45 감별 지식 참조, 서사·인물 창작)",
  "demographicsRule": {
    "fixed": {
      "location": "외래",
      "gender": "여성"
    },
    "recommended": {
      "age": "35~55세"
    },
    "randomizable": [
      "이름",
      "경제적 수준",
      "학력 수준",
      "직업",
      "키",
      "몸무게"
    ],
    "mustAbsent": []
  },
  "scenarioRule": {
    "caseSummary": "석 달 새 세 번, 세상이 빙글빙글 도는 어지럼이 한두 시간씩 지속되는 발작을 겪은 환자. 발작 전엔 왼쪽 귀가 먹먹해지고 윙윙거리는 소리가 커지며, 발작 후엔 왼쪽 귀가 잘 안 들리는 느낌이 남는다.",
    "mustInclude": [
      "회전성 어지럼 발작 20분~수 시간(BPPV보다 김)",
      "3개월 3회 반복",
      "좌측 이명·귀 충만감이 발작 전 악화",
      "좌측 청력 저하 변동성",
      "오심·구토 동반",
      "머리 위치와 무관(BPPV 감별)"
    ],
    "preferredVariants": [
      "짠 음식 즐김",
      "스트레스·과로 시 발작"
    ],
    "mustAbsent": [
      "두통·조짐(전정 편두통 감별은 물으면 없음)",
      "신경학적 증상",
      "귀 통증·분비물",
      "위치 유발(눕거나 돌아누울 때 유발 아님)"
    ]
  },
  "pastHistoryRule": {
    "mustInclude": [
      "특별한 질환 없음"
    ],
    "mustAbsent": [
      "귀 수술·중이염",
      "편두통"
    ]
  },
  "familyHistoryRule": {
    "recommended": [
      "특이 가족력 없음"
    ],
    "mustAbsent": []
  },
  "socialHistoryRule": {
    "fixed": [
      "짠 음식 선호"
    ],
    "recommended": [
      "과로"
    ]
  },
  "physicalExamRule": [
    {
      "item": "활력징후·기립",
      "method": "활력징후·기립 혈압 측정",
      "expectedFinding": "정상, 기립성 저하 없음"
    },
    {
      "item": "안진",
      "method": "안진·안구운동 검사",
      "expectedFinding": "발작 사이 시기 — 자발 안진 없음"
    },
    {
      "item": "두위검사",
      "method": "Dix-Hallpike 검사",
      "expectedFinding": "음성 (위치성 아님)"
    },
    {
      "item": "평형·보행",
      "method": "Romberg·보행 검사",
      "expectedFinding": "정상"
    },
    {
      "item": "신경·소뇌",
      "method": "소뇌기능·신경학적 검사",
      "expectedFinding": "정상"
    },
    {
      "item": "빈혈",
      "method": "결막 확인",
      "expectedFinding": "정상"
    },
    {
      "item": "청력",
      "method": "청력 검사(Weber·Rinne)",
      "expectedFinding": "Weber 우측 편위 — 좌측 감각신경성 난청 시사",
      "polarity": "positive"
    }
  ],
  "liveApiContext": {
    "patientContextFocus": "메니에르병 의심 케이스. '지속시간(시간 단위)+청각 증상 삼합(이명·충만감·난청)+위치 무관'이 BPPV·전정신경염과의 감별 축. 청력 검사(Weber·Rinne)를 실제 수행하는 훈련.",
    "answerPolicy": [
      "먼저 병명을 말하지 않는다.",
      "학생이 묻는 항목에 대해서만 환자 관점에서 짧게 답한다.",
      "고정-부재 단서는 질문받으면 없다고 답한다."
    ],
    "positiveClues": [
      "1~2시간 회전성 발작 반복",
      "발작 전 이명·귀 충만감",
      "변동성 청력 저하",
      "Weber 편위",
      "위치 무관"
    ],
    "negativeClues": [
      "Dix-Hallpike 음성",
      "신경학적 정상",
      "두통·조짐 없음",
      "귀 분비물 없음"
    ]
  },
  "evaluationUse": {
    "mustAsk": [
      "발작 지속시간(시간 단위)",
      "청각 증상(이명·충만감·난청)",
      "위치 유발 여부 확인",
      "반복 패턴",
      "두통·조짐 배제",
      "신경 증상 배제",
      "염분·생활 요인"
    ],
    "positiveClues": [
      "1~2시간 회전성 발작 반복",
      "발작 전 이명·귀 충만감",
      "변동성 청력 저하",
      "Weber 편위",
      "위치 무관"
    ],
    "negativeClues": [
      "Dix-Hallpike 음성",
      "신경학적 정상",
      "두통·조짐 없음",
      "귀 분비물 없음"
    ],
    "educationTopics": [
      "메니에르병 설명 — 속귀 림프액 압력의 문제",
      "저염식이 기본 치료임을 구체적으로(국물·젓갈)",
      "발작 시 안전 확보·구토약 사용",
      "청력검사·이비인후과 연계, 반복 시 예방약"
    ]
  },
  "additionalPromptRule": [],
  "ruleText": "# 증례명 : 어지럼 (메니에르병 의심) — 메니에르병 의심 (Suspected Meniere disease)\n\n- 인적사항 - 성별: 여성(고정), 나이: 35~55세, 장소: 외래\n\n- 사례 요약 - 석 달 새 세 번, 세상이 빙글빙글 도는 어지럼이 한두 시간씩 지속되는 발작을 겪은 환자. 발작 전엔 왼쪽 귀가 먹먹해지고 윙윙거리는 소리가 커지며, 발작 후엔 왼쪽 귀가 잘 안 들리는 느낌이 남는다.\n\n- 감정 상태 - 발작이 또 올까 불안함.\n\n- 현 병력 - 3개월 3회 회전성 어지럼 발작(1~2시간). 발작 전 좌측 귀 충만감·이명 악화, 발작 후 청력 저하 잔존. 오심·구토. 위치 무관. 짠 음식·과로 연관. 두통·신경 증상 없음.\n\n- 과거력 - 특별한 질환 없음.\n\n- 가족력 - 특이 가족력 없음\n\n- 사회력 - 짠 음식 즐김, 커피 2잔, 과로 잦음\n\n- 신체진찰 - 활력징후·기립 혈압 측정: 정상, 기립성 저하 없음 / 안진·안구운동 검사: 발작 사이 시기 — 자발 안진 없음 / Dix-Hallpike 검사: 음성 (위치성 아님) / Romberg·보행 검사: 정상 / 소뇌기능·신경학적 검사: 정상 / 결막 확인: 정상 / 청력 검사(Weber·Rinne): Weber 우측 편위 — 좌측 감각신경성 난청 시사\n\n추가 질문 \"귀가 점점 안 들리게 되는 건가요? 수술해야 하나요?\"",
  "rawRuleText": "# 증례명 : 어지럼 (메니에르병 의심) — 메니에르병 의심 (Suspected Meniere disease)\n\n- 인적사항 - 성별: 여성(고정), 나이: 35~55세, 장소: 외래\n\n- 사례 요약 - 석 달 새 세 번, 세상이 빙글빙글 도는 어지럼이 한두 시간씩 지속되는 발작을 겪은 환자. 발작 전엔 왼쪽 귀가 먹먹해지고 윙윙거리는 소리가 커지며, 발작 후엔 왼쪽 귀가 잘 안 들리는 느낌이 남는다.\n\n- 감정 상태 - 발작이 또 올까 불안함.\n\n- 현 병력 - 3개월 3회 회전성 어지럼 발작(1~2시간). 발작 전 좌측 귀 충만감·이명 악화, 발작 후 청력 저하 잔존. 오심·구토. 위치 무관. 짠 음식·과로 연관. 두통·신경 증상 없음.\n\n- 과거력 - 특별한 질환 없음.\n\n- 가족력 - 특이 가족력 없음\n\n- 사회력 - 짠 음식 즐김, 커피 2잔, 과로 잦음\n\n- 신체진찰 - 활력징후·기립 혈압 측정: 정상, 기립성 저하 없음 / 안진·안구운동 검사: 발작 사이 시기 — 자발 안진 없음 / Dix-Hallpike 검사: 음성 (위치성 아님) / Romberg·보행 검사: 정상 / 소뇌기능·신경학적 검사: 정상 / 결막 확인: 정상 / 청력 검사(Weber·Rinne): Weber 우측 편위 — 좌측 감각신경성 난청 시사\n\n추가 질문 \"귀가 점점 안 들리게 되는 건가요? 수술해야 하나요?\""
}
