{
  "version": 2,
  "type": "rule",
  "id": "rem_sleep_behavior_disorder_rule",
  "title": "렘수면 행동장애 RBD",
  "category": "수면장애",
  "classificationStandard": "주호소 분류 근거: 한국보건의료인국가시험원(국시원) 공개 CPX 진료문항 항목표 CPX 02 '수면장애' — 국가시험 공개 표준 분류이며 특정 교재의 편집·배열을 따른 것이 아님. 개별 시나리오의 인물·서사·대사·수치는 자체 창작.",
  "targetDiagnosis": "렘수면 행동장애",
  "variant": "고령 남성 꿈-행동 일치형",
  "description": "새벽녘 꿈 내용과 실제 주먹질·발길질·고함이 일치하고 각성 후 꿈을 생생히 기억하는 RBD 규칙입니다.",
  "tags": [
    "수면장애",
    "RBD",
    "렘수면행동장애",
    "잠꼬대",
    "퇴행성질환"
  ],
  "sourceTextFile": "# 증례명  렘수면 행동장애 (REM Sleep Behavior.txt",
  "demographicsRule": {
    "fixed": {
      "gender": "남성",
      "age": "70세~79세",
      "location": "외래"
    },
    "recommended": {
      "occupation": "은퇴자·경비원·농부 등 고령층 직업군",
      "bodyWeight": "정상 범위"
    },
    "randomizable": [
      "이름",
      "경제적 수준",
      "학력 수준",
      "키",
      "몸무게"
    ],
    "mustAbsent": [
      "비만 소견"
    ]
  },
  "scenarioRule": {
    "caseSummary": "70대 남성이 새벽녘 꿈을 꾸며 주먹질·발길질·고함 등 과격한 행동을 보여 가족과 본인이 다칠 위험이 있어 내원.",
    "mustInclude": [
      "1~2년 전 시작 후 최근 6개월 악화",
      "새벽 3~6시 발생",
      "꿈 내용과 행동이 일치",
      "깨우면 즉시 명료하고 꿈 내용을 생생히 기억",
      "배우자 또는 본인 부상 위험"
    ],
    "preferredVariants": [
      "격투형 꿈",
      "도망형 꿈",
      "고함형 꿈",
      "술·스트레스·피로 후 악화",
      "초기 루이소체 치매/파킨슨 감별 단서 가능"
    ],
    "mustAbsent": [
      "낮에 갑자기 쓰러지듯 잠듦",
      "심한 코골이·무호흡",
      "몽유병처럼 기억상실/몽롱함",
      "간질 발작 소견"
    ]
  },
  "pastHistoryRule": {
    "mustInclude": [
      "고혈압/고지혈증 약 복용 가능",
      "수면 영향 없는 약 또는 항우울제 유발성 감별 가능"
    ],
    "mustAbsent": [
      "입원력",
      "수술력",
      "알레르기"
    ]
  },
  "familyHistoryRule": {
    "recommended": [
      "파킨슨/치매 가족력 가능 또는 특이사항 없음"
    ],
    "mustAbsent": []
  },
  "socialHistoryRule": {
    "fixed": [],
    "recommended": [
      "반주 음주 가능",
      "술 마신 날 악화",
      "비흡연 또는 오래전 금연",
      "커피 1~2잔"
    ]
  },
  "physicalExamRule": [
    {
      "item": "신경학적 진찰",
      "method": "파킨슨 징후, 보행, 손떨림, 인지기능 확인",
      "expectedFinding": "조합에 따라 초기 퇴행성 단서 가능"
    },
    {
      "item": "외상 확인",
      "method": "타박상·찰과상 확인",
      "expectedFinding": "수면 중 행동으로 인한 상처 가능",
      "examConceptId": "skin_injury_inspection"
    }
  ],
  "liveApiContext": {
    "patientContextFocus": "낮에는 온순하지만 밤에 꿈을 행동으로 옮겨 가족을 다치게 할까 걱정하는 고령 남성 환자.",
    "answerPolicy": [
      "먼저 병명을 말하지 않는다.",
      "학생이 묻는 항목에 대해서만 환자 관점에서 짧게 답한다.",
      "고정-부재 단서는 질문받으면 없다고 답한다."
    ],
    "positiveClues": [
      "꿈-행동 일치",
      "새벽녘 발생",
      "각성 후 즉시 명료",
      "꿈 내용 생생히 기억",
      "과격한 잠꼬대/주먹질/발길질"
    ],
    "negativeClues": [
      "기면증 양상 없음",
      "수면무호흡 단서 없음",
      "몽유병식 기억상실 없음"
    ]
  },
  "evaluationUse": {
    "mustAsk": [
      "발생 시간대",
      "꿈 내용 기억 여부",
      "각성 후 의식 상태",
      "행동과 꿈의 일치",
      "동거인/본인 부상",
      "약물/항우울제",
      "파킨슨·인지저하·환시·후각저하·변비",
      "코골이·무호흡 감별",
      "기면증/몽유병/간질 감별"
    ],
    "positiveClues": [
      "꿈-행동 일치",
      "새벽녘 발생",
      "각성 후 즉시 명료",
      "꿈 내용 생생히 기억",
      "과격한 잠꼬대/주먹질/발길질"
    ],
    "negativeClues": [
      "기면증 양상 없음",
      "수면무호흡 단서 없음",
      "몽유병식 기억상실 없음"
    ],
    "educationTopics": [
      "수면다원검사",
      "침실 안전조치",
      "약물치료 가능성",
      "퇴행성 질환 추적 필요성"
    ]
  },
  "additionalPromptRule": [],
  "ruleText": "# 증례명 : 렘수면 행동장애 (REM Sleep Behavior Disorder, RBD)\nCPX 워크시트 \n\n- 인적사항 -\n성별 : 남성  \n\n나이 : 70대 고령층 (70세~79세 사이 랜덤 설정)  \n\n이름 : 임의 설정 (예: 고만석, 박장호 등)\n\n경제적 수준 : 중하 ~ 중위 수준 (직업군 배경에 따라 유연하게 설정)\n\n학력 수준 : 고졸 이하 또는 대졸 (직업 배경에 맞춤)\n\n직업 : 은퇴자, 아파트 경비원, 농부 등 고령층 직업군 중 랜덤 설정  \n\n키 : 정상 범위 (특별한 비만 소견 없음)\n\n몸무게 : 정상 범위 \n\n장소 : 외래  \n\n\n- 사례 요약 -\n평소 온순하고 자상한 성격의 70대 남성 환자가 1~2년 전 시작되어 최근 6개월간 급격히 악화된 수면 중 과격한 잠꼬대 및 거친 신체 행동(주먹질, 발길질, 고함 등)을 주소로 외래에 내원하였습니다. 증상은 주로 새벽녘(새벽 3시~6시)에 발생하며, 꿈 내용과 실제 신체 행동이 완벽히 일치하는 양상을 보입니다. 깨웠을 때 몽롱함 없이 즉시 정신을 바짝 차리며 꿈 내용을 생생히 기억하는 것이 핵심 특징입니다. 이 증례는 순수 특발성 RBD뿐만 아니라 70대 고령에서 동반 위험이 높은 퇴행성 질환(초기 루이소체 치매, 파킨슨병)으로의 이행 가능성을 의사가 정확히 감별 문진해내는지 테스트하는 고난도 시나리오입니다.  \n\n\n- 성격 및 감정 상태 -\n○ 평소 성격: 평소에는 온순하고 자상하며 무난한 성격입니다. 밤에 보이는 거친 행동 양상과는 전혀 다른 반전 성격을 가지고 있습니다.  \n\n\n○ 현재 감정 상태: 나이 먹고 혹시 몹쓸 치매나 이상한 정신병에 걸린 것은 아닌가 싶어 속으로 몹시 불안해하고 두려워하는 상태입니다. (방어형 선택 시: 귀찮아하고 무덤덤해하려 노력함)  \n\n\n○ 지금 상황: 수면 중 주먹질이나 침대 밖으로 뛰어내리는 거친 행동 때문에 옆에서 자던 아내가 맞아서 다치거나 본인 머리가 깨지는 등 부상 위험이 지속해서 발생하는 심각한 상황입니다.  \n\n\n○ 지금 가장 걱정되는 것: 사랑하는 아내를 잠결에 때려 더 크게 다치게 하거나, 자신의 뇌가 완전히 망가지는 치매/파킨슨 같은 무서운 병의 초기 증상일까 봐 가장 걱정됩니다.  \n\n\n○ 지금 기대하는 것: 의사가 친절하고 전문적으로 이 병의 원인을 짚어주고, 정말 치매 같은 큰 병인지 명확히 판별해 주며, 밤에 안심하고 잘 수 있도록 실질적인 약물이나 해결책을 주기를 기대합니다.\n\n- 현 병력 -\n주소증: \"낮에는 멀쩡한데 밤에 자다가 저도 모르게 고함을 지르거나 주먹질, 발길질을 해서 가족들이 다치고 난리가 납니다.\"  \n\n\n발병 시점 및 경과: 1~2년 전 잠꼬대로 시작했으나, 최근 6개월 전부터 과격한 신체 행동이나 비명으로 급격히 악화되었습니다 (서서히 진행하는 양상).  \n\n빈도: 처음엔 한 달에 1~2번이던 것이 최근에는 일주일에 2~3번으로 매우 잦아졌습니다.  \n\n발생 시간: 주로 잠들고 한참 뒤인 새벽녘 (새벽 3시 ~ 새벽 6시 사이) 렘수면 단계에서 발생합니다.  \n\n\n수면 행동 양상 (아래 중 1개 무작위 선택):\n\nA 유형 (격투형): 꿈에서 도둑, 괴한, 혹은 사나운 동물과 육탄전으로 싸우며 주먹질/발길질을 함. 주로 옆에서 자던 배우자가 걷어차이거나 맞아서 다침.  \n\nB 유형 (도망형): 옛날 군대 시절 적군에게 쫓기거나, 벼랑 끝에서 떨어지거나, 불길로부터 탈출하는 꿈을 꿈. 꿈속에서 도망치다가 침대 밖으로 뛰어내리거나 굴러떨어져 머리가 깨지거나 본인이 크게 다침.  \n\nC 유형 (고함형): 누군가와 심하게 말다툼을 하거나 호통을 치는 꿈을 꿈. 밤새 큰 소리로 욕을 하거나 비명을 질러 가족들이 깜짝 놀라 잠을 깸.  \n\n\nRBD 필수 의학적 특징 (고정 조건):\n꿈-행동 일치: 꿈속 내용과 실제 몸짓이 완벽히 일치함.  \n\n각성 후 의식: 증상을 보일 때 주변에서 흔들어 깨우면 몽롱함 없이 즉시 정신이 바짝 들고 꿈 내용을 생생하게 기억함 (잠결에 치매 증상처럼 헛소리를 하거나 사람을 못 알아보는 게 아님).  \n\n악화 요인: 유독 스트레스를 많이 받거나, 낮에 텃밭 가꾸기 등 몸을 많이 써서 피곤한 날, 혹은 저녁에 반주로 술을 마신 날 밤에 증상이 훨씬 더 심해짐.  \n\n배제 조건: 낮에 갑자기 쓰러지듯 잠들거나(기면증 배제), 심하게 코를 골며 숨을 멈추는 증상(수면무호흡 배제)은 없음.  \n\n- 과거력 -\n○ 평소: 수면 중 이상 행동이 생기기 전까지는 특별한 이상 없이 규칙적으로 생활해 왔음.\n\n○ 약물 복용 (아래 중 1개 무작위 선택):\n\n복용중인 약 없음.\n\n약물 X: 일반적인 고혈압, 고지혈증 약만 복용 중 (수면 영향 없음).  \n\n약물 Y (약물 유발성 감별): 1년 전부터 가벼운 우울감과 수면 장애로 정신건강의학과에서 항우울제(SSRI 계열 등)를 처방받아 꾸준히 복용 중임 (의사가 항우울제 부작용 가능성을 문진하는지 확인용).  \n\n\n○ 질환: 고혈압 및 고지혈증으로 10년째 약 복용 중 혹은 무지병.  \n\n○ 알레르기: 없음.\n\n○ 수술: 없음.\n\n○ 입원: 없음.\n\n- 가족력 -\n가족력 설정 (아래 중 1개 무작위 선택):\n\n가족력 A : 특이사항 없음. 부모님 모두 수면 문제나 신경계 질환 없이 노환으로 돌아가심.  \n\n가족력 B (유전적 퇴행성 힌트) : 돌아가신 아버지가 노년에 손을 심하게 떠셨고 행동이 아주 느려지셨으며, 돌아가시기 전에는 사람을 잘 못 알아보는 치매 증상이 있으셨음 (퇴행성 질환인 루이소체 치매나 파킨슨병 가계 소인 감별을 위한 핵심 힌트).  \n\n- 사회력 -\n술 : (O), 자주 마시지는 않으나 일주일에 1~2회 정도 저녁 식사 때 반주로 소주 반병~1병 정도 마심. 술 마신 날 밤에는 확실히 발길질이나 잠꼬대 증상이 훨씬 더 심해짐.  \n\n담배 : (X), 비흡연자 (또는 과거에 피웠으나 오래전 금연함).\n\n커피 : (O), 낮에 피로를 예방하기 위해 하루에 1~2잔 정도 규칙적으로 마심.\n\n\n\n[환자가 70대일 경우 특화형: 퇴행성 질환 및 치매 연관 증상 감별 변수]\n(의사가 인지기능 저하 및 환시, 이상운동 증상을 꼼꼼히 체크하는지 확인하기 위해 아래 3가지 조합 중 1개가 무작위 지정됨)\n\n조합 1 (초기 루이소체 치매 진입형):\n\n인지 기능: 최근 6개월 전부터 약속을 자주 깜빡하고 했던 말을 또 함. 특이하게 어떤 날은 정신이 아주 맑은데, 어떤 날은 하루 종일 멍하고 집중을 전혀 못 하는 등 '기복(Fluctuation)'이 매우 심함.  \n\n\n환시: 늦은 오후나 밤에 거실 구석이나 벽에 \"모르는 아이나 조그만 동물(고양이 등)이 가만히 앉아 있다가 사라지는 것\"을 몇 번 생생하게 봄. (정신 나간 사람 취급받을까 봐 의사가 묻기 전엔 절대 먼저 말 안 함).  \n\n\n기타: 수년 전부터 냄새를 잘 맡지 못하는 후각 저하와 만성 변비가 동반되어 있음. 손떨림이나 보행장애는 아직 없음.  \n\n\n조합 2 (파킨슨병 동반형):\n\n\n운동 증상: 최근 들어 오른손 끝이 가만히 쉴 때 미세하게 부르르 떨리고(안정 시 진전), 걸음걸이가 둔해지며 몸이 전체적으로 뻣뻣함. 표정이 다소 무뚝뚝해졌다는 소리를 주변에서 들음.  \n\n\n인지/환시: 인지 기능은 나이에 비해 정상이며, 벽에 헛것이 보이는 증상(환시)도 전혀 없음.  \n\n\n기타: 후각이나 배변은 정상임.  \n\n\n조합 3 (순수 특발성 RBD형):\n\n\n인지/운동 모두 정상: 후각, 배변, 운동 능력, 기억력 모두 아주 정상이며 헛것을 보는 증상도 전혀 없음. 오직 밤에 잠버릇만 험한 상태임.  \n\n\n[환자의 성격 및 태도 설정 (의사-환자 관계 평가 변수)]\n(아래 중 1개 무작위 선택)\n\n선택 1 (협조적/불안형): 나이 먹고 몹쓸 치매나 이상한 정신병에 걸린 건 아닌가 싶어 속으로 몹시 불안해하며 의사의 질문에 아주 성실하고 진지하게 대답하고 적극적으로 조언을 구함.  \n\n\n선택 2 (비협조적/방어형): \"나이 70 넘으면 다 기억력도 깜빡하고 잠버릇도 험해지는 거지, 마누라가 별것도 아닌 걸로 유난을 떨어서 억지로 왔다\"며 귀찮아하고 증상을 은연중에 축소·숨기려 함.  \n\n\n- 신체진찰방법 -\n의사가 환자의 퇴행성 신경계 질환 합병 여부를 걸러내기 위해 다음과 같은 신체 진찰을 직접 수행하는지 평가합니다.\n\n정신 상태 및 인지 기능 검사: 시간/장소 지남력 검사 및 3가지 단어 회상 등 간이 인지 평가(MMSE 등)를 시도하는가?\n\n운동계 진찰 (강직 및 진전 확인): 환자의 팔다리 관절을 직접 수동적으로 굽혔다 펴보며 뻣뻣함(강직, Rigidity)이 있는지 확인하고, 가만히 앉아있을 때 손떨림(안정 시 진전)이 나타나는지 유심히 관찰하는가?\n\n보행 및 자세 검사: 환자에게 진료실 내를 직접 걸어보게 하여 보폭이 좁아졌는지, 걸을 때 팔 흔들기가 감소했는지, 신체 균형을 잘 잡는지 확인하는가?",
  "rawRuleText": "# 증례명 : 렘수면 행동장애 (REM Sleep Behavior Disorder, RBD)\nCPX 워크시트 \n\n- 인적사항 -\n성별 : 남성  \n\n나이 : 70대 고령층 (70세~79세 사이 랜덤 설정)  \n\n이름 : 임의 설정 (예: 고만석, 박장호 등)\n\n경제적 수준 : 중하 ~ 중위 수준 (직업군 배경에 따라 유연하게 설정)\n\n학력 수준 : 고졸 이하 또는 대졸 (직업 배경에 맞춤)\n\n직업 : 은퇴자, 아파트 경비원, 농부 등 고령층 직업군 중 랜덤 설정  \n\n키 : 정상 범위 (특별한 비만 소견 없음)\n\n몸무게 : 정상 범위 \n\n장소 : 외래  \n\n\n- 사례 요약 -\n평소 온순하고 자상한 성격의 70대 남성 환자가 1~2년 전 시작되어 최근 6개월간 급격히 악화된 수면 중 과격한 잠꼬대 및 거친 신체 행동(주먹질, 발길질, 고함 등)을 주소로 외래에 내원하였습니다. 증상은 주로 새벽녘(새벽 3시~6시)에 발생하며, 꿈 내용과 실제 신체 행동이 완벽히 일치하는 양상을 보입니다. 깨웠을 때 몽롱함 없이 즉시 정신을 바짝 차리며 꿈 내용을 생생히 기억하는 것이 핵심 특징입니다. 이 증례는 순수 특발성 RBD뿐만 아니라 70대 고령에서 동반 위험이 높은 퇴행성 질환(초기 루이소체 치매, 파킨슨병)으로의 이행 가능성을 의사가 정확히 감별 문진해내는지 테스트하는 고난도 시나리오입니다.  \n\n\n- 성격 및 감정 상태 -\n○ 평소 성격: 평소에는 온순하고 자상하며 무난한 성격입니다. 밤에 보이는 거친 행동 양상과는 전혀 다른 반전 성격을 가지고 있습니다.  \n\n\n○ 현재 감정 상태: 나이 먹고 혹시 몹쓸 치매나 이상한 정신병에 걸린 것은 아닌가 싶어 속으로 몹시 불안해하고 두려워하는 상태입니다. (방어형 선택 시: 귀찮아하고 무덤덤해하려 노력함)  \n\n\n○ 지금 상황: 수면 중 주먹질이나 침대 밖으로 뛰어내리는 거친 행동 때문에 옆에서 자던 아내가 맞아서 다치거나 본인 머리가 깨지는 등 부상 위험이 지속해서 발생하는 심각한 상황입니다.  \n\n\n○ 지금 가장 걱정되는 것: 사랑하는 아내를 잠결에 때려 더 크게 다치게 하거나, 자신의 뇌가 완전히 망가지는 치매/파킨슨 같은 무서운 병의 초기 증상일까 봐 가장 걱정됩니다.  \n\n\n○ 지금 기대하는 것: 의사가 친절하고 전문적으로 이 병의 원인을 짚어주고, 정말 치매 같은 큰 병인지 명확히 판별해 주며, 밤에 안심하고 잘 수 있도록 실질적인 약물이나 해결책을 주기를 기대합니다.\n\n- 현 병력 -\n주소증: \"낮에는 멀쩡한데 밤에 자다가 저도 모르게 고함을 지르거나 주먹질, 발길질을 해서 가족들이 다치고 난리가 납니다.\"  \n\n\n발병 시점 및 경과: 1~2년 전 잠꼬대로 시작했으나, 최근 6개월 전부터 과격한 신체 행동이나 비명으로 급격히 악화되었습니다 (서서히 진행하는 양상).  \n\n빈도: 처음엔 한 달에 1~2번이던 것이 최근에는 일주일에 2~3번으로 매우 잦아졌습니다.  \n\n발생 시간: 주로 잠들고 한참 뒤인 새벽녘 (새벽 3시 ~ 새벽 6시 사이) 렘수면 단계에서 발생합니다.  \n\n\n수면 행동 양상 (아래 중 1개 무작위 선택):\n\nA 유형 (격투형): 꿈에서 도둑, 괴한, 혹은 사나운 동물과 육탄전으로 싸우며 주먹질/발길질을 함. 주로 옆에서 자던 배우자가 걷어차이거나 맞아서 다침.  \n\nB 유형 (도망형): 옛날 군대 시절 적군에게 쫓기거나, 벼랑 끝에서 떨어지거나, 불길로부터 탈출하는 꿈을 꿈. 꿈속에서 도망치다가 침대 밖으로 뛰어내리거나 굴러떨어져 머리가 깨지거나 본인이 크게 다침.  \n\nC 유형 (고함형): 누군가와 심하게 말다툼을 하거나 호통을 치는 꿈을 꿈. 밤새 큰 소리로 욕을 하거나 비명을 질러 가족들이 깜짝 놀라 잠을 깸.  \n\n\nRBD 필수 의학적 특징 (고정 조건):\n꿈-행동 일치: 꿈속 내용과 실제 몸짓이 완벽히 일치함.  \n\n각성 후 의식: 증상을 보일 때 주변에서 흔들어 깨우면 몽롱함 없이 즉시 정신이 바짝 들고 꿈 내용을 생생하게 기억함 (잠결에 치매 증상처럼 헛소리를 하거나 사람을 못 알아보는 게 아님).  \n\n악화 요인: 유독 스트레스를 많이 받거나, 낮에 텃밭 가꾸기 등 몸을 많이 써서 피곤한 날, 혹은 저녁에 반주로 술을 마신 날 밤에 증상이 훨씬 더 심해짐.  \n\n배제 조건: 낮에 갑자기 쓰러지듯 잠들거나(기면증 배제), 심하게 코를 골며 숨을 멈추는 증상(수면무호흡 배제)은 없음.  \n\n- 과거력 -\n○ 평소: 수면 중 이상 행동이 생기기 전까지는 특별한 이상 없이 규칙적으로 생활해 왔음.\n\n○ 약물 복용 (아래 중 1개 무작위 선택):\n\n복용중인 약 없음.\n\n약물 X: 일반적인 고혈압, 고지혈증 약만 복용 중 (수면 영향 없음).  \n\n약물 Y (약물 유발성 감별): 1년 전부터 가벼운 우울감과 수면 장애로 정신건강의학과에서 항우울제(SSRI 계열 등)를 처방받아 꾸준히 복용 중임 (의사가 항우울제 부작용 가능성을 문진하는지 확인용).  \n\n\n○ 질환: 고혈압 및 고지혈증으로 10년째 약 복용 중 혹은 무지병.  \n\n○ 알레르기: 없음.\n\n○ 수술: 없음.\n\n○ 입원: 없음.\n\n- 가족력 -\n가족력 설정 (아래 중 1개 무작위 선택):\n\n가족력 A : 특이사항 없음. 부모님 모두 수면 문제나 신경계 질환 없이 노환으로 돌아가심.  \n\n가족력 B (유전적 퇴행성 힌트) : 돌아가신 아버지가 노년에 손을 심하게 떠셨고 행동이 아주 느려지셨으며, 돌아가시기 전에는 사람을 잘 못 알아보는 치매 증상이 있으셨음 (퇴행성 질환인 루이소체 치매나 파킨슨병 가계 소인 감별을 위한 핵심 힌트).  \n\n- 사회력 -\n술 : (O), 자주 마시지는 않으나 일주일에 1~2회 정도 저녁 식사 때 반주로 소주 반병~1병 정도 마심. 술 마신 날 밤에는 확실히 발길질이나 잠꼬대 증상이 훨씬 더 심해짐.  \n\n담배 : (X), 비흡연자 (또는 과거에 피웠으나 오래전 금연함).\n\n커피 : (O), 낮에 피로를 예방하기 위해 하루에 1~2잔 정도 규칙적으로 마심.\n\n\n\n[환자가 70대일 경우 특화형: 퇴행성 질환 및 치매 연관 증상 감별 변수]\n(의사가 인지기능 저하 및 환시, 이상운동 증상을 꼼꼼히 체크하는지 확인하기 위해 아래 3가지 조합 중 1개가 무작위 지정됨)\n\n조합 1 (초기 루이소체 치매 진입형):\n\n인지 기능: 최근 6개월 전부터 약속을 자주 깜빡하고 했던 말을 또 함. 특이하게 어떤 날은 정신이 아주 맑은데, 어떤 날은 하루 종일 멍하고 집중을 전혀 못 하는 등 '기복(Fluctuation)'이 매우 심함.  \n\n\n환시: 늦은 오후나 밤에 거실 구석이나 벽에 \"모르는 아이나 조그만 동물(고양이 등)이 가만히 앉아 있다가 사라지는 것\"을 몇 번 생생하게 봄. (정신 나간 사람 취급받을까 봐 의사가 묻기 전엔 절대 먼저 말 안 함).  \n\n\n기타: 수년 전부터 냄새를 잘 맡지 못하는 후각 저하와 만성 변비가 동반되어 있음. 손떨림이나 보행장애는 아직 없음.  \n\n\n조합 2 (파킨슨병 동반형):\n\n\n운동 증상: 최근 들어 오른손 끝이 가만히 쉴 때 미세하게 부르르 떨리고(안정 시 진전), 걸음걸이가 둔해지며 몸이 전체적으로 뻣뻣함. 표정이 다소 무뚝뚝해졌다는 소리를 주변에서 들음.  \n\n\n인지/환시: 인지 기능은 나이에 비해 정상이며, 벽에 헛것이 보이는 증상(환시)도 전혀 없음.  \n\n\n기타: 후각이나 배변은 정상임.  \n\n\n조합 3 (순수 특발성 RBD형):\n\n\n인지/운동 모두 정상: 후각, 배변, 운동 능력, 기억력 모두 아주 정상이며 헛것을 보는 증상도 전혀 없음. 오직 밤에 잠버릇만 험한 상태임.  \n\n\n[환자의 성격 및 태도 설정 (의사-환자 관계 평가 변수)]\n(아래 중 1개 무작위 선택)\n\n선택 1 (협조적/불안형): 나이 먹고 몹쓸 치매나 이상한 정신병에 걸린 건 아닌가 싶어 속으로 몹시 불안해하며 의사의 질문에 아주 성실하고 진지하게 대답하고 적극적으로 조언을 구함.  \n\n\n선택 2 (비협조적/방어형): \"나이 70 넘으면 다 기억력도 깜빡하고 잠버릇도 험해지는 거지, 마누라가 별것도 아닌 걸로 유난을 떨어서 억지로 왔다\"며 귀찮아하고 증상을 은연중에 축소·숨기려 함.  \n\n\n- 신체진찰방법 -\n의사가 환자의 퇴행성 신경계 질환 합병 여부를 걸러내기 위해 다음과 같은 신체 진찰을 직접 수행하는지 평가합니다.\n\n정신 상태 및 인지 기능 검사: 시간/장소 지남력 검사 및 3가지 단어 회상 등 간이 인지 평가(MMSE 등)를 시도하는가?\n\n운동계 진찰 (강직 및 진전 확인): 환자의 팔다리 관절을 직접 수동적으로 굽혔다 펴보며 뻣뻣함(강직, Rigidity)이 있는지 확인하고, 가만히 앉아있을 때 손떨림(안정 시 진전)이 나타나는지 유심히 관찰하는가?\n\n보행 및 자세 검사: 환자에게 진료실 내를 직접 걸어보게 하여 보폭이 좁아졌는지, 걸을 때 팔 흔들기가 감소했는지, 신체 균형을 잘 잡는지 확인하는가?"
}
